README.rst
setup.py
django_seo_admin.egg-info/PKG-INFO
django_seo_admin.egg-info/SOURCES.txt
django_seo_admin.egg-info/dependency_links.txt
django_seo_admin.egg-info/top_level.txt
seo/__init__.py
seo/admin.py
seo/models.py
seo/utils.py
seo/templatetags/__init__.py
seo/templatetags/tag_seo_admin.py