Metadata-Version: 1.1
Name: django-seo-admin
Version: 0.2
Summary: App for apply SEO on your websites with Django.
Home-page: https://github.com/mapeveri/django-seo-admin
Author: Peveri Martin
Author-email: martinpeveri@gmail.com
License: BSD License
Platform: UNKNOWN
Classifier: Environment :: Web Environment
Classifier: Framework :: Django
Classifier: Intended Audience :: Developers
Classifier: License :: OSI Approved :: BSD License
Classifier: Operating System :: OS Independent
Classifier: Programming Language :: Python
Classifier: Programming Language :: Python :: 2.7
Classifier: Topic :: Internet :: WWW/HTTP
Classifier: Topic :: Internet :: WWW/HTTP :: Dynamic Content
